easy_overlay/__init__.py
easy_overlay-0.0.6.dist-info/METADATA
easy_overlay-0.0.6.dist-info/WHEEL
easy_overlay-0.0.6.dist-info/top_level.txt
easy_overlay-0.0.6.dist-info/RECORD
